{"name":"DRAW:PAGE","attrs":{"DRAW:NAME":"page8","DRAW:STYLE-NAME":"dp1","DRAW:MASTER-PAGE-NAME":"\u9810\u8a2d_5f_","PRESENTATION:PRESENTATION-PAGE-LAYOUT-NAME":"AL1T19","FO:MARGIN-TOP":"0cm","FO:MARGIN-BOTTOM":"0cm","FO:MARGIN-LEFT":"0cm","FO:MARGIN-RIGHT":"0cm","FO:PAGE-WIDTH":"28cm","FO:PAGE-HEIGHT":"21cm","STYLE:PRINT-ORIENTATION":"landscape"},"children":[{"name":"OFFICE:FORMS","attrs":{"FORM:AUTOMATIC-FOCUS":"false","FORM:APPLY-DESIGN-MODE":"false"}},{"name":"DRAW:FRAME","attrs":{"DRAW:STYLE-NAME":"gr1","DRAW:TEXT-STYLE-NAME":"P1","DRAW:LAYER":"layout","SVG:WIDTH":"27.978cm","SVG:HEIGHT":"20.978cm","SVG:X":"0.005cm","SVG:Y":"0.011cm","textarea-vertical-align":"middle","opacity":1},"children":[{"name":"DRAW:IMAGE","attrs":{"XLINK:HREF":"Pictures\/1000000000000400000003001B355C08.jpg","XLINK:TYPE":"simple","XLINK:SHOW":"embed","XLINK:ACTUATE":"onLoad"},"children":[{"name":"TEXT:P","attrs":[]}]}]},{"name":"DRAW:FRAME","attrs":{"PRESENTATION:STYLE-NAME":"pr4","DRAW:TEXT-STYLE-NAME":"P5","DRAW:LAYER":"layout","SVG:WIDTH":"14.8cm","SVG:HEIGHT":"4.483cm","SVG:X":"2.4cm","SVG:Y":"2.4cm","PRESENTATION:CLASS":"title","PRESENTATION:USER-TRANSFORMED":"true","textarea-vertical-align":"middle","text-align":"center","font-size":"44pt","font-style":"normal","text-shadow":"none","font-weight":"normal","font-family":"'Liberation Sans';\u5fae\u8edf\u6b63\u9ed1\u9ad4;Mangal"},"children":[{"name":"DRAW:TEXT-BOX","attrs":[],"children":[{"name":"TEXT:P","attrs":{"TEXT:STYLE-NAME":"P2","FO:LINE-HEIGHT":"100%"},"children":[{"name":"TEXT:SPAN","attrs":{"TEXT:STYLE-NAME":"T1","font-size":"30pt","font-family":"'Noto Sans S Chinese Medium';'Noto Sans S Chinese Medium'"},"text":"\u561f\u561f\uff01\u4f60\u5728\u8aaa\u4ec0\u9ebc\uff1f"}]}]}]},{"name":"PRESENTATION:NOTES","attrs":{"DRAW:STYLE-NAME":"dp2"},"children":[{"name":"OFFICE:FORMS","attrs":{"FORM:AUTOMATIC-FOCUS":"false","FORM:APPLY-DESIGN-MODE":"false"}},{"name":"DRAW:PAGE-THUMBNAIL","attrs":{"DRAW:STYLE-NAME":"gr2","DRAW:LAYER":"layout","SVG:WIDTH":"14.848cm","SVG:HEIGHT":"11.136cm","SVG:X":"3.075cm","SVG:Y":"2.257cm","DRAW:PAGE-NUMBER":"8","PRESENTATION:CLASS":"page"}},{"name":"DRAW:FRAME","attrs":{"PRESENTATION:STYLE-NAME":"pr3","DRAW:TEXT-STYLE-NAME":"P4","DRAW:LAYER":"layout","SVG:WIDTH":"16.799cm","SVG:HEIGHT":"13.364cm","SVG:X":"2.1cm","SVG:Y":"14.107cm","PRESENTATION:CLASS":"notes","PRESENTATION:PLACEHOLDER":"true","font-size":"28.1000003814697pt","font-style":"normal","text-shadow":"none","font-weight":"normal","font-family":"'Liberation Sans';\u5fae\u8edf\u6b63\u9ed1\u9ad4;Mangal","background-color":"#ffffff"},"children":[{"name":"DRAW:TEXT-BOX","attrs":{"data":[{"id":"5217","traditional":"\u4ec0","simplified":"\u4ec0","pinyin_numbers":"shen2","pinyin_marks":"sh\u00e9n","translation":"what"},{"id":"5218","traditional":"\u4ec0","simplified":"\u4ec0","pinyin_numbers":"shi2","pinyin_marks":"sh\u00ed","translation":"ten (used in fractions, writing checks etc)\/assorted\/miscellaneous"},{"id":"5229","traditional":"\u4ec0\u9ebc","simplified":"\u4ec0\u4e48","pinyin_numbers":"shen2 me5","pinyin_marks":"sh\u00e9n me","translation":"what?\/who?\/something\/anything"},{"id":"6578","traditional":"\u4f60","simplified":"\u4f60","pinyin_numbers":"ni3","pinyin_marks":"n\u01d0","translation":"you (informal, as opposed to courteous \u60a8[nin2])"},{"id":"20618","traditional":"\u561f","simplified":"\u561f","pinyin_numbers":"du1","pinyin_marks":"d\u016b","translation":"toot\/honk\/to pout"},{"id":"22105","traditional":"\u5728","simplified":"\u5728","pinyin_numbers":"zai4","pinyin_marks":"z\u00e0i","translation":"(located) at\/(to be) in\/to exist\/in the middle of doing sth\/(indicating an action in progress)"},{"id":"89181","traditional":"\u8aaa","simplified":"\u8bf4","pinyin_numbers":"shui4","pinyin_marks":"shu\u00ec","translation":"to persuade"},{"id":"89182","traditional":"\u8aaa","simplified":"\u8bf4","pinyin_numbers":"shuo1","pinyin_marks":"shu\u014d","translation":"to speak\/to say\/to explain\/to scold\/to tell off\/a theory (usually in compounds such as \u65e5\u5fc3\u8bf4 heliocentric theory)"},{"id":"89241","traditional":"\u8aaa\u8aaa","simplified":"\u8bf4\u8bf4","pinyin_numbers":"shuo1 shuo5","pinyin_marks":"shu\u014d shuo","translation":"to say sth"},{"id":"108913","traditional":"\u9ebc","simplified":"\u4e48","pinyin_numbers":"ma2","pinyin_marks":"m\u00e1","translation":"exclamatory final particle"},{"id":"108914","traditional":"\u9ebc","simplified":"\u4e48","pinyin_numbers":"ma5","pinyin_marks":"ma","translation":"interrogative final particle"},{"id":"108915","traditional":"\u9ebc","simplified":"\u4e48","pinyin_numbers":"me5","pinyin_marks":"me","translation":"suffix, used to form interrogative \u751a\u9ebc|\u4ec0\u4e48[shen2 me5], what?, indefinite \u9019\u9ebc|\u8fd9\u4e48[zhe4 me5] thus, etc"},{"id":"108916","traditional":"\u9ebc","simplified":"\u9ebd","pinyin_numbers":"mo2","pinyin_marks":"m\u00f3","translation":"tiny\/insignificant"},{"id":"108917","traditional":"\u9ebc\u9ebc","simplified":"\u4e48\u4e48","pinyin_numbers":"me5 me5","pinyin_marks":"me me","translation":"kissing sound (slang onom.)"}]}}]}]}]}