{
  "non_radical_stroke_count": 4,
  "title": "冰",
  "radical": "<a href=\"#~冫\">冫</a>",
  "stroke_count": 6,
  "heteronyms": [
    {
      "definitions": [
        {
          "example": [
            "例⃝<span class='punct'>「<a href=\"#~結冰\">結冰</a>」、</span><span class='punct'>「<a href=\"#~冰霜\">冰霜</a>」。</span>"
          ],
          "def": "<a href=\"#~水\">水</a><a href=\"#~在\">在</a>0℃<a href=\"#~以下\">以下</a><a href=\"#~所\">所</a><a href=\"#~凝結\">凝結</a><a href=\"#~成\">成</a><a href=\"#~的\">的</a><span class='punct'><a href=\"#~固體\">固體</a>。</span>"
        },
        {
          "example": [
            "例⃝<span class='punct'>「<a href=\"#~冰涼\">冰涼</a></span><a href=\"#~的\">的</a><span class='punct'><a href=\"#~飲料\">飲料</a>」、</span><span class='punct'>「<a href=\"#~泳池\">泳池</a></span><a href=\"#~的\">的</a><a href=\"#~水\">水</a><a href=\"#~很\">很</a><span class='punct'><a href=\"#~冰\">冰</a>，</span><a href=\"#~弟弟\">弟弟</a><a href=\"#~怕\">怕</a><a href=\"#~冷\">冷</a><a href=\"#~不敢\">不敢</a><span class='punct'><a href=\"#~下水\">下水</a>」。</span>"
          ],
          "def": "<a href=\"#~形容\">形容</a><a href=\"#~感覺\">感覺</a><a href=\"#~溫度\">溫度</a><a href=\"#~非常\">非常</a><span class='punct'><a href=\"#~低\">低</a>。</span>"
        },
        {
          "example": [
            "例⃝<span class='punct'>「<a href=\"#~冰\">冰</a></span><a href=\"#~過\">過</a><a href=\"#~的\">的</a><a href=\"#~啤酒\">啤酒</a><a href=\"#~好\">好</a><span class='punct'><a href=\"#~喝\">喝</a>」、</span><span class='punct'>「<a href=\"#~買\">買</a></span><a href=\"#~回來\">回來</a><a href=\"#~的\">的</a><a href=\"#~魚\">魚</a><a href=\"#~要\">要</a><a href=\"#~冰\">冰</a><span class='punct'><a href=\"#~起來\">起來</a>，</span><a href=\"#~才\">才</a><a href=\"#~可以\">可以</a><a href=\"#~保持\">保持</a><span class='punct'><a href=\"#~新鮮\">新鮮</a>」。</span>"
          ],
          "def": "<a href=\"#~使用\">使用</a><a href=\"#~冷凍\">冷凍</a><a href=\"#~設備\">設備</a><a href=\"#~或\">或</a><a href=\"#~冰涼\">冰涼</a><a href=\"#~的\">的</a><span class='punct'><a href=\"#~物品\">物品</a>，</span><a href=\"#~來\">來</a><a href=\"#~降低\">降低</a><span class='punct'><a href=\"#~溫度\">溫度</a>，</span><a href=\"#~以\">以</a><a href=\"#~保持\">保持</a><a href=\"#~物品\">物品</a><span class='punct'><a href=\"#~新鮮\">新鮮</a>。</span>"
        },
        {
          "example": [
            "例⃝<span class='punct'>「<a href=\"#~冰心\">冰心</a>」、</span><span class='punct'>「<a href=\"#~冰\">冰</a></span><span class='punct'><a href=\"#~清\">清</a>」、</span><span class='punct'>「<a href=\"#~冰\">冰</a></span><a href=\"#~肌\">肌</a><a href=\"#~玉\">玉</a><span class='punct'><a href=\"#~膚\">膚</a>」。</span>"
          ],
          "def": "<a href=\"#~形容\">形容</a><span class='punct'><a href=\"#~清高\">清高</a>、</span><span class='punct'><a href=\"#~潔白\">潔白</a>。</span>"
        },
        {
          "example": [
            "例⃝<span class='punct'>「<a href=\"#~他\">他</a></span><a href=\"#~的\">的</a><a href=\"#~態度\">態度</a><a href=\"#~很\">很</a><span class='punct'><a href=\"#~冰\">冰</a>，</span><a href=\"#~令\">令</a><a href=\"#~人\">人</a><a href=\"#~難以\">難以</a><span class='punct'><a href=\"#~親近\">親近</a>」。</span>"
          ],
          "def": "<a href=\"#~比喻\">比喻</a><a href=\"#~非常\">非常</a><a href=\"#~不\">不</a><span class='punct'><a href=\"#~熱情\">熱情</a>；</span><span class='punct'><a href=\"#~冷酷\">冷酷</a>。</span>"
        },
        {
          "example": [
            "例⃝<span class='punct'>「<a href=\"#~冰片\">冰片</a>」、</span><span class='punct'>「<a href=\"#~冰糖\">冰糖</a>」。</span>"
          ],
          "def": "<a href=\"#~像\">像</a><a href=\"#~冰\">冰</a><a href=\"#~一樣\">一樣</a><span class='punct'><a href=\"#~的\">的</a>。</span>"
        },
        {
          "def": "<span class='punct'><a href=\"#~姓\">姓</a>。</span>"
        }
      ],
      "id": "1003090000",
      "pinyin": "bīng",
      "bopomofo": "ㄅㄧㄥ"
    }
  ],
  "translation": {
    "Deutsch": [
      "Eis (S)​",
      "einfrieren (V)​",
      "mit Eis kühlen (V)​"
    ],
    "English": [
      "ice",
      "CL:<a href=\"#~塊\">塊</a>|块[kuai4]",
      "methamphetamine (slang)​"
    ]
  },
  "xrefs": []
}